{"batch_size": 128, "n_val_tasks": 1000, "n_val_ways": 5, "num_epochs": 200, "evaluate_every": 5, "momentum_slope": 0.01, "final_momentum": 0.9, "learning_rate": 0.001, "seed": 2, "left_classif_factor": 0.7, "right_classif_factor": 0.7, "siamese_factor": 1.0, "quantization": "none", "lr_annealing": true, "momentum_annealing": true, "optimizer": "sgd", "console_print": true, "plot_training_images": false, "plot_val_images": false, "plot_test_images": false, "plot_confusion": false, "plot_wrong_preds": false, "results_path": "/mnt/Storage/code/low-shot/siamese_on_edge_tf2/results/2020_6_22-11_43_43_966415_seed_2_tiny-imagenet_HorizontalNetworkV44_quantization_none_classif_yes", "chkpt": null, "model": "HorizontalNetworkV44", "save_weights": true, "write_to_tensorboard": true, "dataset": "tiny-imagenet", "data_path": "/mnt/data/siamese_cluster_new/data", "image_dims": [64, 64, 3], "dataset_path": "/mnt/data/siamese_cluster_new/data/tiny-imagenet", "with_classif": "yes"}